{
  "setting": {
    "compileHotReLoad": false,
    "urlCheck": false
  },
  "condition": {
    "miniprogram": {
      "list": [
        {
          "name": "",
          "pathName": "pages/Order/Coupon/Coupon",
          "query": "goods_id=9&coupon_id=3",
          "launchMode": "default",
          "scene": null
        },
        {
          "name": "",
          "pathName": "pages/MergeFit/MergeFit",
          "query": "",
          "launchMode": "default",
          "scene": null
        },
        {
          "name": "",
          "pathName": "pages/ConfirmOrder/ConfirmOrder",
          "query": "goods_id=1&user_point=547",
          "launchMode": "default",
          "scene": null
        },
        {
          "name": "",
          "pathName": "pages/Order/Order",
          "query": "",
          "launchMode": "default",
          "scene": null
        },
        {
          "name": "管理员",
          "pathName": "pages/check/check",
          "query": "",
          "launchMode": "default",
          "scene": null
        },
        {
          "name": "兑换记录",
          "pathName": "pages/Order/Order",
          "query": "",
          "launchMode": "default",
          "scene": null
        },
        {
          "name": "确认订单",
          "pathName": "pages/ConfirmOrder/ConfirmOrder",
          "query": "",
          "launchMode": "default",
          "scene": null
        },
        {
          "name": "",
          "pathName": "pages/Rank/Rank",
          "query": "",
          "launchMode": "default",
          "scene": null
        },
        {
          "name": "",
          "pathName": "pages/user-info/user-info",
          "query": "",
          "launchMode": "default",
          "scene": null
        },
        {
          "name": "pages/CyclingRecord/CyclingRecord",
          "pathName": "pages/CyclingRecord/CyclingRecord",
          "query": "",
          "scene": null
        }
      ]
    }
  },
  "description": "项目私有配置文件。此文件中的内容将覆盖 project.config.json 中的相同字段。项目的改动优先同步到此文件中。详见文档：https://developers.weixin.qq.com/miniprogram/dev/devtools/projectconfig.html",
  "projectname": "%E5%B0%BC%E5%85%8B%E4%B9%8B%E6%98%9F"
}